<ClinicalDocument xmlns="urn:hl7-org:v3" xmlns:mif="urn:hl7-org:v3/mif" xmlns:xsi="http://www.w3.org/2001/XMLSchema-instance" xsi:schemaLocation="urn:hl7-org:v3 ..sdschemasSDA.xsd">
    <realmCode code="CN"/>
    <typeId extension="POCD_MT000040" root="2.16.840.1.113883.1.3"/>
    <templateId root="2.16.156.10011.2.1.1.56"/>
    <id extension="586641136" root="2.16.156.10011.1.1"/>
    <code code="C0036" codeSystem="2.16.156.10011.2.4" codeSystemName="卫生信息共享文档规范编码体系"/>
    <title>24h内入院死亡记录</title>
    <effectiveTime value="20211102182729"/>
    <confidentialityCode code="N" codeSystem="2.16.840.1.113883.5.25" codeSystemName="Confidentiality" displayName="正常访问保密级别"/>
    <languageCode code="zh-CN"/>
    <setId/>
    <versionNumber/>
    <recordTarget contextControlCode="OP" typeCode="RCT">
        <patientRole classCode="PAT">
            <id extension="586641" root="2.16.156.10011.1.12"/>
            <addr use="H">
                <houseNumber/>
                <streetName/>
                <township/>
                <county/>
                <city/>
                <state/>
            </addr>
            <patient classCode="PSN" determinerCode="INSTANCE">
                <id extension="586641" root="2.16.156.10011.1.3"/>
                <name>燕文峰</name>
                <administrativeGenderCode code="1" codeSystem="2.16.156.10011.2.3.3.4" codeSystemName="生理性别代码表(GB/T 2261.1)" displayName="男性"/>
                <maritalStatusCode code="20" codeSystem="2.16.156.10011.2.3.3.5" codeSystemName="婚姻状况代码表(GB/T 2261.2)" displayName="已婚"/>
                <ethnicGroupCode code="01" codeSystem="2.16.156.10011.2.3.3.3" codeSystemName="民族类别代码表(GB 3304)" displayName="汉族"/>
                <age unit="岁" value="52"/>
                <occupation>
                    <occupationCode code="90" codeSystem="2.16.156.10011.2.3.3.13" codeSystemName="从业状况(个人身体)代码表(GB/T 2261.4)" displayName="其他"/>
                </occupation>
            </patient>
        </patientRole>
    </recordTarget>
    <author contextControlCode="OP" typeCode="AUT">
        <time value="20211102182729"/>
        <assignedAuthor classCode="ASSIGNED">
            <id extension="HXNLS" root="2.16.156.10011.1.7"/>
            <assignedPerson>
                <name>刘爽</name>
            </assignedPerson>
        </assignedAuthor>
    </author>
    <custodian typeCode="CST">
        <assignedCustodian classCode="ASSIGNED">
            <representedCustodianOrganization classCode="ORG" determinerCode="INSTANCE">
                <id extension="49438123-6" root="2.16.156.10011.1.5"/>
                <name>济南市人民医院</name>
            </representedCustodianOrganization>
        </assignedCustodian>
    </custodian>
    <legalAuthenticator>
        <time value="20211102182729"/>
        <signatureCode/>
        <assignedEntity>
            <id extension="HXNLS" root="2.16.156.10011.1.4"/>
            <code displayName="主任医师"/>
            <assignedPerson>
                <name>刘爽</name>
            </assignedPerson>
        </assignedEntity>
    </legalAuthenticator>
    <authenticator>
        <time value="20211102182729"/>
        <signatureCode/>
        <assignedEntity>
            <id extension="Y15WHB" root="2.16.156.10011.1.4"/>
            <code displayName="主治医师"/>
            <assignedPerson>
                <name>王海滨</name>
            </assignedPerson>
        </assignedEntity>
    </authenticator>
    <authenticator>
        <time value="20211102182729"/>
        <signatureCode/>
        <assignedEntity>
            <id extension="Y15WHB" root="2.16.156.10011.1.4"/>
            <code displayName="住院医师"/>
            <assignedPerson>
                <name>王海滨</name>
            </assignedPerson>
        </assignedEntity>
    </authenticator>
    <authenticator>
        <time value="20211102182729"/>
        <signatureCode/>
        <assignedEntity>
            <id extension="HXNLS" root="2.16.156.10011.1.4"/>
            <code displayName="接诊医师"/>
            <assignedPerson>
                <name>刘爽</name>
            </assignedPerson>
        </assignedEntity>
    </authenticator>
    <relatedDocument typeCode="RPLC">
        <parentDocument>
            <id/>
            <setId/>
            <versionNumber/>
        </parentDocument>
    </relatedDocument>
    <componentOf>
        <encompassingEncounter>
            <effectiveTime>
                <low value="20211102182729"/>
            </effectiveTime>
        </encompassingEncounter>
    </componentOf>
    <component>
        <structuredBody>
            <component>
                <section>
                    <code code="10154-3" codeSystem="2.16.840.1.113883.6.1" codeSystemName="LOINC" displayName="CHIEF COMPLAINT"/>
                    <text/>
                    <entry>
                        <observation classCode="OBS" moodCode="EVN">
                            <code code="DE04.01.119.00" codeSystem="2.16.156.10011.2.2.1" codeSystemName="卫生信息数据元目录" displayName="主诉"/>
                            <value xsi:type="ST">确诊肺癌1年余，纳差1周，喘憋加重1天。</value>
                        </observation>
                    </entry>
                </section>
            </component>
            <component>
                <section>
                    <code code="11450-4" codeSystem="2.16.840.1.113883.6.1" codeSystemName="LOINC" displayName="PROBLEM LIST"/>
                    <text/>
                    <entry>
                        <observation classCode="OBS" moodCode="EVN">
                            <code code="DE05.10.143.00" codeSystem="2.16.156.10011.2.2.1" codeSystemName="卫生信息数据元目录" displayName="陈述内容可靠标志"/>
                            <value value="true" xsi:type="BL"/>
                        </observation>
                    </entry>
                </section>
            </component>
            <component>
                <section>
                    <code code="46241-6" codeSystem="2.16.840.1.113883.6.1" codeSystemName="LOINC" displayName="HOSPITAL ADMISSION DX"/>
                    <text/>
                    <entry>
                        <observation classCode="OBS" moodCode="EVN">
                            <code code="DE05.01.025.00" codeSystem="2.16.156.10011.2.2.1" codeSystemName="卫生信息数据元目录" displayName="入院诊断-西医诊断名称"/>
                            <value xsi:type="ST">肺占位性病变</value>
                            <entryRelationship typeCode="COMP">
                                <observation classCode="OBS" moodCode="EVN">
                                    <code code="DE05.01.024.00" codeSystem="2.16.156.10011.2.2.1" codeSystemName="卫生信息数据元目录" displayName="入院诊断-西医诊断编码"/>
                                    <value code="R91.x03" codeSystem="2.16.156.10011.2.3.3.11" codeSystemName="ICD-10" displayName="肺占位性病变" xsi:type="CD"/>
                                </observation>
                            </entryRelationship>
                        </observation>
                    </entry>
                    <entry>
                        <observation classCode="OBS" moodCode="EVN">
                            <code code="DE05.10.172.00" codeSystem="2.16.156.10011.2.2.1" codeSystemName="卫生信息数据元目录" displayName="入院诊断-中医病名名称"/>
                            <value xsi:type="ST">其他证</value>
                            <entryRelationship typeCode="COMP">
                                <observation classCode="OBS" moodCode="EVN">
                                    <code code="DE05.10.130.00" codeSystem="2.16.156.10011.2.2.1" codeSystemName="卫生信息数据元目录" displayName="入院诊断-中医病名代码"/>
                                    <value code="ZVV000" codeSystem="2.16.156.10011.2.3.3.14" codeSystemName="中医病证分类与代码表( GB/T 15657)" displayName="其他证" xsi:type="CD"/>
                                </observation>
                            </entryRelationship>
                            <entryRelationship typeCode="COMP">
                                <observation classCode="OBS" moodCode="EVN">
                                    <code code="DE05.10.172.00" codeSystem="2.16.156.10011.2.2.1" codeSystemName="卫生信息数据元目录" displayName="入院诊断-中医证候名称"/>
                                    <value xsi:type="ST">其他证</value>
                                </observation>
                            </entryRelationship>
                            <entryRelationship typeCode="COMP">
                                <observation classCode="OBS" moodCode="EVN">
                                    <code code="DE05.10.130.00" codeSystem="2.16.156.10011.2.2.1" codeSystemName="卫生信息数据元目录" displayName="入院诊断-中医证候代码"/>
                                    <value code="ZVV000" codeSystem="2.16.156.10011.2.3.3.14" codeSystemName="中医病证分类与代码表( GB/T 15657)" displayName="其他证" xsi:type="CD"/>
                                </observation>
                            </entryRelationship>
                        </observation>
                    </entry>
                </section>
            </component>
            <component>
                <section>
                    <code code="18776-5" codeSystem="2.16.840.1.113883.6.1" codeSystemName="LOINC" displayName="TREATMENT PLAN"/>
                    <text/>
                    <entry>
                        <observation classCode="OBS" moodCode="INT">
                            <code code="DE06.00.300.00" codeSystem="2.16.156.10011.2.2.1" codeSystemName="卫生信息数据元目录" displayName="治则治法"/>
                            <value xsi:type="ST">-</value>
                        </observation>
                    </entry>
                </section>
            </component>
            <component>
                <section>
                    <code code="8648-8" codeSystem="2.16.840.1.113883.6.1" codeSystemName="LOINC" displayName="HOSPITAL COURSE"/>
                    <text/>
                    <entry>
                        <observation classCode="OBS" moodCode="EVN">
                            <code code="DE05.10.148.00" codeSystem="2.16.156.10011.2.2.1" codeSystemName="卫生信息数据元目录" displayName="入院情况"/>
                            <value xsi:type="ST">患者因确诊肺癌1年余，纳差1周，喘憋加重1天入院。既往体健。1年余前患者因“咳嗽、喘憋2月余”来院住院治疗，行肺CT示：左肺上叶阻塞性炎症，纵膈及左肺门增大淋巴结。肺内淡结节灶，转移？左侧胸水，左肺下叶部分不张实变。局限性肺气肿。心包少量积液。肝囊肿。给予抗感染治疗，择期行支气管镜，病理示小细胞神经内分泌癌。建议免疫+化疗。患者及家属选择化疗。给予依托泊苷+顺铂方案化疗5周期。化疗后消化道反应明显，骨髓抑制反应轻。后再次住院复查肺CT同前片比较，左侧胸腔积液量较前增多，纵膈淋巴结较前增大，考虑病变较前进展，现有化疗方案效果不佳，建议1.加用免疫治疗。2.加用放疗。3.更换化疗方案。患者及家属商量后决定更换化疗方案，后给予“洛铂50mg d1+伊立替康90mg d1、d8”方案化疗3周期，复查肺CT考虑病情较前进展，建议首选加用英飞凡免疫制剂，或者口服安罗替尼。次选替雷利珠单抗，家属经商量后决定继续应用原化疗方案+替雷利珠单抗治疗，治疗期间患者出现咯血，给予止血及对症治疗后好转。后患者因经济原因拒绝继续免疫治疗,选择再次给予3周期洛铂50mg d1+伊立替康90mg d1、d8治疗。化疗期音出现骨髓抑制，给予对症处理可好转。于2021-07-18出院。2月前患者咳嗽频繁，时有胸痛出现，剑突下明显，呈绞痛，持续10-30分钟好转，阵发性，疼痛时排便感觉明显，行肺CT示：左肺上叶阻塞性炎症，纵膈及左肺门增大淋巴结。肺内淡结节灶，转移？左侧胸水，左肺下叶部分不张实变。局限性肺气肿。心包少量积液。肝囊肿。给予左侧胸腔闭式引流，症状缓解。1周前患者出现乏力纳差，1天前喘憋加重明显，急来我院就诊。于急诊复查肺CT示右侧胸腔积液增多，大量心包积液，给予右侧胸腔闭式引流，喘憋缓解不明显，为行进一步治疗，收入我科。查体：BP：77/54mmHg,血氧饱和度78%，端坐位，反应迟钝，精神萎糜，面色灰暗，四肢湿瘫，听诊双肺呼吸音低,未闻及干湿性罗音，心音低，心率118次/分，各瓣膜听诊区未闻及病理性杂音，腹软，肝脾未及，双下肢无明显水肿。辅助检查：肺CT：左肺下叶中心型肺癌，纵隔浸润。纵隔淋巴结转移，左肺阻塞性肺不张表现。心包积液。双侧胸腔积液，右肺上叶肺气肿，右侧肾上腺转移瘤。心肌标志物：肌红蛋白 416.34ng/ml,肌酸激酶同功酶 7.12ng/ml。BNP前体 405.4pg/</value>
                        </observation>
                    </entry>
                    <entry>
                        <observation classCode="OBS" moodCode="EVN">
                            <code code="DE06.00.296.00" codeSystem="2.16.156.10011.2.2.1" codeSystemName="卫生信息数据元目录" displayName="诊疗过程描述"/>
                            <value xsi:type="ST">入院后给予心电监护，血压77/54mmHg,血氧饱和度78%，心率118次/分，病情危重，向患者家属讲明病情，下达病危，家属表示对病情理解，拒绝行有创抢救措施，给予升压，扩容等对症处理，但患者病情持续恶化，于11：30出现呼之不应，瞳孔散大固定，呼吸浅慢，持续静滴多巴胺，于11：45呼吸停止，心率下降，11：48行心电图检查呈直线，宣布临床死亡。</value>
                        </observation>
                    </entry>
                    <entry>
                        <observation classCode="OBS" moodCode="EVN">
                            <code code="DE05.10.099.00" codeSystem="2.16.156.10011.2.2.1" codeSystemName="卫生信息数据元目录" displayName="死亡原因"/>
                            <value xsi:type="ST">多脏器功能衰竭</value>
                        </observation>
                    </entry>
                    <entry>
                        <observation classCode="OBS" moodCode="EVN">
                            <code code="DE05.01.025.00" codeSystem="2.16.156.10011.2.2.1" codeSystemName="卫生信息数据元目录" displayName="死亡诊断-西医诊断名称"/>
                            <value xsi:type="ST">原发性支气管肺癌（小细胞型,广泛期）</value>
                            <entryRelationship typeCode="COMP">
                                <observation classCode="OBS" moodCode="EVN">
                                    <code code="DE05.01.024.00" codeSystem="2.16.156.10011.2.2.1" codeSystemName="卫生信息数据元目录" displayName="死亡诊断-西医诊断编码"/>
                                    <value code="C34.900x001" codeSystem="2.16.156.10011.2.3.3.11" codeSystemName="ICD-10" displayName="原发性支气管肺癌（小细胞型,广泛期）" xsi:type="CD"/>
                                </observation>
                            </entryRelationship>
                        </observation>
                    </entry>
                    <entry>
                        <observation classCode="OBS" moodCode="EVN">
                            <code code="DE02.01.036.00" codeSystem="2.16.156.10011.2.2.1" codeSystemName="卫生信息数据元目录" displayName="死亡日期时间"/>
                            <effectiveTime>
                                <high value="20211102114800"/>
                            </effectiveTime>
                        </observation>
                    </entry>
                    <entry>
                        <observation classCode="OBS" moodCode="EVN">
                            <code code="DE05.10.172.00" codeSystem="2.16.156.10011.2.2.1" codeSystemName="卫生信息数据元目录" displayName="死亡诊断-中医病名名称"/>
                            <value xsi:type="ST">其他证</value>
                            <entryRelationship typeCode="COMP">
                                <observation classCode="OBS" moodCode="EVN">
                                    <code code="DE05.10.130.00" codeSystem="2.16.156.10011.2.2.1" codeSystemName="卫生信息数据元目录" displayName="死亡诊断-中医病名代码"/>
                                    <value code="ZVV000" codeSystem="2.16.156.10011.2.3.3.14" codeSystemName="中医病证分类与代码表( GB/T 15657)" displayName="其他证" xsi:type="CD"/>
                                </observation>
                            </entryRelationship>
                            <entryRelationship typeCode="COMP">
                                <observation classCode="OBS" moodCode="EVN">
                                    <code code="DE05.10.172.00" codeSystem="2.16.156.10011.2.2.1" codeSystemName="卫生信息数据元目录" displayName="死亡诊断-中医证候名称"/>
                                    <value xsi:type="ST">其他证</value>
                                </observation>
                            </entryRelationship>
                            <entryRelationship typeCode="COMP">
                                <observation classCode="OBS" moodCode="EVN">
                                    <code code="DE05.10.130.00" codeSystem="2.16.156.10011.2.2.1" codeSystemName="卫生信息数据元目录" displayName="死亡诊断-中医证候代码"/>
                                    <value code="ZVV000" codeSystem="2.16.156.10011.2.3.3.14" codeSystemName="中医病证分类与代码表( GB/T 15657)" displayName="其他证" xsi:type="CD"/>
                                </observation>
                            </entryRelationship>
                        </observation>
                    </entry>
                </section>
            </component>
        </structuredBody>
    </component>
</ClinicalDocument>
