<?xml version="1.0" encoding="UTF-8"?>
<ClinicalDocument xmlns="urn:hl7-org:v3" xmlns:mif="urn:hl7-org:v3/mif" xmlns:xsi="http://www.w3.org/2001/XMLSchema-instance" xsi:schemaLocation="urn:hl7-org:v3 ..\sdschemas\SDA.xsd">
    <!--
********************************************************
Header
********************************************************
-->
    <realmCode code="CN"/>
    <typeId extension="POCD_MT000040" root="2.16.840.1.113883.1.3"/>
    <templateId root="2.16.156.10011.2.1.1.30"/>
    <!-- 文档流水号 -->
    <id extension="4976792C0010" root="2.16.156.10011.1.1"/>
    <code code="C0010" codeSystem="2.16.156.10011.2.4" codeSystemName="卫生信息共享文档编码体系"/>
    <title>麻醉术前访视记录</title>
    <!-- 文档机器生成时间 -->
    <effectiveTime value="20211112154500"/>
    <confidentialityCode code="N" codeSystem="2.16.840.1.113883.5.25" codeSystemName="Confidentiality" displayName="正常访问保密级别"/>
    <languageCode code="zh-CN"/>
    <setId/>
    <versionNumber/>
    <!--文档记录对象(患者) [1..*] contextControlCode="OP"表示本信息可以被重载-->
    <recordTarget contextControlCode="OP" typeCode="RCT">
        <patientRole classCode="PAT">
            <!--门诊号标识-->
            <id extension="497679" root="2.16.156.10011.1.11"/>
            <!--住院号标识-->
            <id extension="497679" root="2.16.156.10011.1.12"/>
            <!--电子申请单编号-->
            <id extension="49767981" root="2.16.156.10011.1.24"/>
            <patient classCode="PSN" determinerCode="INSTANCE">
                <!--患者身份证号标识-->
                <id extension="37091919580319006X" root="2.16.156.10011.1.3"/>
                <name>高秀芹</name>
                <administrativeGenderCode code="2" codeSystem="2.16.156.10011.2.3.3.4" codeSystemName="生理性别代码表(GB/T 2261.1)" displayName="女性"/>
                <!-- 年龄 -->
                <age unit="岁" value="63"/>
            </patient>
        </patientRole>
    </recordTarget>
    <!-- 文档创作者 -->
    <author contextControlCode="OP" typeCode="AUT">
        <time value="20211112154500"/>
        <assignedAuthor classCode="ASSIGNED">
            <id extension="01109" root="2.16.156.10011.1.7"/>
            <assignedPerson>
                <name>李如珍</name>
            </assignedPerson>
        </assignedAuthor>
    </author>
    <!-- 保管机构 -->
    <custodian typeCode="CST">
        <assignedCustodian classCode="ASSIGNED">
            <representedCustodianOrganization classCode="ORG" determinerCode="INSTANCE">
                <id extension="49438123-6" root="2.16.156.10011.1.5"/>
                <name>济南市人民医院</name>
            </representedCustodianOrganization>
        </assignedCustodian>
    </custodian>
    <!--麻醉医师签名-->
    <authenticator>
        <!--签名日期时间-->
        <time value="20211112133000"/>
        <signatureCode/>
        <assignedEntity>
            <id extension="01109" root="2.16.156.10011.1.4"/>
            <code displayName="麻醉医师"/>
            <assignedPerson>
                <name>李如珍</name>
            </assignedPerson>
        </assignedEntity>
    </authenticator>
    <relatedDocument typeCode="RPLC">
        <parentDocument>
            <id/>
            <setId/>
            <versionNumber/>
        </parentDocument>
    </relatedDocument>
    <!-- 病床号、病房、病区、科室和医院的关联 -->
    <componentOf>
        <encompassingEncounter>
            <!-- 入院日期时间 -->
            <effectiveTime value="20211109082901"/>
            <location>
                <healthCareFacility>
                    <serviceProviderOrganization>
                        <asOrganizationPartOf classCode="PART">
                            <!-- DE01.00.026.00	病床号 -->
                            <wholeOrganization classCode="ORG" determinerCode="INSTANCE">
                                <id extension="22" root="2.16.156.10011.1.22"/>
                                <name>22</name>
                                <!-- DE01.00.019.00	病房号 -->
                                <asOrganizationPartOf classCode="PART">
                                    <wholeOrganization classCode="ORG" determinerCode="INSTANCE">
                                        <id extension="31010202" root="2.16.156.10011.1.21"/>
                                        <name>泌尿外科二组</name>
                                        <!-- DE08.10.026.00	科室名称 -->
                                        <asOrganizationPartOf classCode="PART">
                                            <wholeOrganization classCode="ORG" determinerCode="INSTANCE">
                                                <id extension="31010202" root="2.16.156.10011.1.26"/>
                                                <name>泌尿外科二组</name>
                                                <!-- DE08.10.054.00	病区名称 -->
                                                <asOrganizationPartOf classCode="PART">
                                                    <wholeOrganization classCode="ORG" determinerCode="INSTANCE">
                                                        <id extension="T031@" root="2.16.156.10011.1.27"/>
                                                        <name>泌尿外科病区护理单元</name>
                                                        <!--XXX医院 -->
                                                        <asOrganizationPartOf classCode="PART">
                                                            <wholeOrganization classCode="ORG" determinerCode="INSTANCE">
                                                                <id extension="49438123-6" root="2.16.156.10011.1.5"/>
                                                                <name>济南市人民医院</name>
                                                            </wholeOrganization>
                                                        </asOrganizationPartOf>
                                                    </wholeOrganization>
                                                </asOrganizationPartOf>
                                            </wholeOrganization>
                                        </asOrganizationPartOf>
                                    </wholeOrganization>
                                </asOrganizationPartOf>
                            </wholeOrganization>
                        </asOrganizationPartOf>
                    </serviceProviderOrganization>
                </healthCareFacility>
            </location>
        </encompassingEncounter>
    </componentOf>
    <!--***************************************************
文档体Body
*******************************************************
-->
    <component>
        <structuredBody>
            <!--
********************************************************
术前诊断章节
********************************************************
-->
            <component>
                <section>
                    <code code="10219-4" codeSystem="2.16.840.1.113883.6.1" codeSystemName="LOINC" displayName="Surgical operation note preoperative Dx"/>
                    <text/>
                    <!--术前诊断-->
                    <entry>
                        <observation classCode="OBS" moodCode="EVN">
                            <!--术前诊断编码-->
                            <code code="DE05.01.024.00" codeSystem="2.16.156.10011.2.2.1" codeSystemName="卫生信息数据元目录" displayName="术前诊断编码"/>
                            <value code="Q85.903" codeSystem="2.16.156.10011.2.3.3.11" codeSystemName="ICD-10" displayName="肾错构瘤" xsi:type="CD"/>
                        </observation>
                    </entry>
                    <!-- 术前合并疾病 -->
                    <entry>
                        <observation classCode="OBS" moodCode="EVN">
                            <code code="DE05.01.076.00" codeSystem="2.16.156.10011.2.2.1" codeSystemName="卫生信息数据元目录" displayName="术前合并疾病"/>
                            <value xsi:type="ST">高血压</value>
                        </observation>
                    </entry>
                </section>
            </component>
            <!--现病史章节-->
            <component>
                <section>
                    <code code="10164-2" codeSystem="2.16.840.1.113883.6.1" codeSystemName="LOINC" displayName="HISTORY OF PRESENT ILLNESS"/>
                    <text/>
                    <!--简要病史条目-->
                    <entry>
                        <observation classCode="OBS" moodCode="EVN">
                            <code code="DE05.10.140.00" codeSystem="2.16.156.10011.2.2.1" codeSystemName="卫生信息数据元目录" displayName="简要病史"/>
                            <value xsi:type="ST">"子宫切除+乳癌根治手术史"</value>
                        </observation>
                    </entry>
                </section>
            </component>
            <!--既往史章节-->
            <component>
                <section>
                    <code code="11348-0" codeSystem="2.16.840.1.113883.6.1" codeSystemName="LOINC" displayName="HISTORY OF PAST ILLNESS"/>
                    <text/>
                    <!--过敏史条目-->
                    <entry>
                        <observation classCode="OBS" moodCode="EVN">
                            <code code="DE02.10.022.00" codeSystem="2.16.156.10011.2.2.1" codeSystemName="卫生信息数据元目录" displayName="过敏史"/>
                            <value xsi:type="ST">头孢及青霉素过敏</value>
                        </observation>
                    </entry>
                </section>
            </component>
            <!--体格检查章节-->
            <component>
                <section>
                    <code code="29545-1" codeSystem="2.16.840.1.113883.6.1" codeSystemName="LOINC" displayName="PHYSICAL EXAMINATION"/>
                    <text/>
                    <!-- 体重 -->
                    <entry>
                        <observation classCode="OBS" moodCode="EVN">
                            <code code="DE04.10.188.00" codeSystem="2.16.156.10011.2.2.1" codeSystemName="卫生信息数据元目录" displayName="入院体重"/>
                            <value unit="kg" value="75.00" xsi:type="PQ"/>
                        </observation>
                    </entry>
                    <entry>
                        <observation classCode="OBS" moodCode="EVN">
                            <code code="DE04.10.019.00" codeSystem="2.16.156.10011.2.2.1" codeSystemName="卫生信息数据元目录" displayName="出生体重"/>
                            <value unit="g" value="4000" xsi:type="PQ"/>
                        </observation>
                    </entry>
                    <!-- 一般状况检查结果 -->
                    <entry>
                        <observation classCode="OBS" moodCode="EVN">
                            <code code="DE04.10.219.00" codeSystem="2.16.156.10011.2.2.1" codeSystemName="卫生信息数据元目录" displayName="一般状况检查结果"/>
                            <value xsi:type="ST">正常</value>
                        </observation>
                    </entry>
                    <!-- 精神状态正常标志 -->
                    <entry>
                        <observation classCode="OBS" moodCode="EVN">
                            <code code="DE05.10.142.00" codeSystem="2.16.156.10011.2.2.1" codeSystemName="卫生信息数据元目录" displayName="精神状态正常标志"/>
                            <value value="true" xsi:type="BL"/>
                        </observation>
                    </entry>
                    <!-- 心脏听诊结果 -->
                    <entry>
                        <observation classCode="OBS" moodCode="EVN">
                            <code code="DE04.10.207.00" codeSystem="2.16.156.10011.2.2.1" codeSystemName="卫生信息数据元目录" displayName="心脏听诊结果"/>
                            <value xsi:type="ST">未闻及杂音</value>
                        </observation>
                    </entry>
                    <!-- 肺部听诊结果 -->
                    <entry>
                        <observation classCode="OBS" moodCode="EVN">
                            <code code="DE04.10.031.00" codeSystem="2.16.156.10011.2.2.1" codeSystemName="卫生信息数据元目录" displayName="肺部听诊结果"/>
                            <value xsi:type="ST">未查</value>
                        </observation>
                    </entry>
                    <!-- 四肢检查结果 -->
                    <entry>
                        <observation classCode="OBS" moodCode="EVN">
                            <code code="DE04.10.179.00" codeSystem="2.16.156.10011.2.2.1" codeSystemName="卫生信息数据元目录" displayName="四肢检查结果"/>
                            <value xsi:type="ST">正常</value>
                        </observation>
                    </entry>
                    <!-- 脊柱检查结果 -->
                    <entry>
                        <observation classCode="OBS" moodCode="EVN">
                            <code code="DE04.10.093.00" codeSystem="2.16.156.10011.2.2.1" codeSystemName="卫生信息数据元目录" displayName="脊柱检查结果"/>
                            <value xsi:type="ST">未查</value>
                        </observation>
                    </entry>
                    <!-- 腹部检查结果 -->
                    <entry>
                        <observation classCode="OBS" moodCode="EVN">
                            <code code="DE04.10.046.00" codeSystem="2.16.156.10011.2.2.1" codeSystemName="卫生信息数据元目录" displayName="腹部检查结果"/>
                            <value xsi:type="ST">未查</value>
                        </observation>
                    </entry>
                    <!-- 气管检查结果 -->
                    <entry>
                        <observation classCode="OBS" moodCode="EVN">
                            <code code="DE06.00.230.00" codeSystem="2.16.156.10011.2.2.1" codeSystemName="卫生信息数据元目录" displayName="气管检查结果"/>
                            <value xsi:type="ST">通畅</value>
                        </observation>
                    </entry>
                    <!-- 牙齿检查结果 -->
                    <entry>
                        <observation classCode="OBS" moodCode="EVN">
                            <code code="DE04.10.264.00" codeSystem="2.16.156.10011.2.2.1" codeSystemName="卫生信息数据元目录" displayName="牙齿检查结果"/>
                            <value xsi:type="ST">部分义齿</value>
                        </observation>
                    </entry>
                </section>
            </component>
            <!--
********************************************************
实验室检查章节
********************************************************
-->
            <component>
                <section>
                    <code code="30954-2" codeSystem="2.16.840.1.113883.6.1" codeSystemName="LOINC" displayName="STUDIES SUMMARY"/>
                    <text/>
                    <entry typeCode="COMP">
                        <!-- 血型-->
                        <organizer classCode="BATTERY" moodCode="EVN">
                            <statusCode/>
                            <component typeCode="COMP">
                                <!-- ABO血型 -->
                                <observation classCode="OBS" moodCode="EVN">
                                    <code code="DE04.50.001.00" codeSystem="2.16.156.10011.2.2.1" codeSystemName="卫生信息数据元目录" displayName="ABO血型代码"/>
                                    <value code="5" codeSystem="2.16.156.10011.2.3.1.85" codeSystemName="ABO血型代码表" displayName="不详" xsi:type="CD"/>
                                </observation>
                            </component>
                            <component typeCode="COMP">
                                <!-- Rh血型 -->
                                <observation classCode="OBS" moodCode="EVN">
                                    <code code="DE04.50.010.00" codeSystem="2.16.156.10011.2.2.1" codeSystemName="卫生信息数据元目录" displayName="Rh（D）血型代码"/>
                                    <value code="4" codeSystem="2.16.156.10011.2.3.1.250" codeSystemName="Rh(D)血型代码表" displayName="未查" xsi:type="CD"/>
                                </observation>
                            </component>
                        </organizer>
                    </entry>
                    <!-- 心电图检查结果 -->
                    <entry>
                        <observation classCode="OBS" moodCode="EVN">
                            <code code="DE04.30.043.00" codeSystem="2.16.156.10011.2.2.1" codeSystemName="卫生信息数据元目录" displayName="心电图检查结果"/>
                            <value xsi:type="ST">T波改变</value>
                        </observation>
                    </entry>
                    <!-- 胸部X线检查结果 -->
                    <entry>
                        <observation classCode="OBS" moodCode="EVN">
                            <code code="DE04.30.045.00" codeSystem="2.16.156.10011.2.2.1" codeSystemName="卫生信息数据元目录" displayName="胸部X线检查结果"/>
                            <value xsi:type="ST">双肺结节灶</value>
                        </observation>
                    </entry>
                    <!-- CT检查结果 -->
                    <entry>
                        <observation classCode="OBS" moodCode="EVN">
                            <code code="DE04.30.005.00" codeSystem="2.16.156.10011.2.2.1" codeSystemName="卫生信息数据元目录" displayName="CT检查结果"/>
                            <value xsi:type="ST">不详</value>
                        </observation>
                    </entry>
                    <!-- B超检查结果 -->
                    <entry>
                        <observation classCode="OBS" moodCode="EVN">
                            <code code="DE04.30.002.00" codeSystem="2.16.156.10011.2.2.1" codeSystemName="卫生信息数据元目录" displayName="B超检查结果"/>
                            <value xsi:type="ST">未查</value>
                        </observation>
                    </entry>
                    <!-- MRI检查结果 -->
                    <entry>
                        <observation classCode="OBS" moodCode="EVN">
                            <code code="DE04.30.009.00" codeSystem="2.16.156.10011.2.2.1" codeSystemName="卫生信息数据元目录" displayName="MRI检查结果"/>
                            <value xsi:type="ST">不详</value>
                        </observation>
                    </entry>
                    <!-- 肺功能检查结果 -->
                    <entry>
                        <observation classCode="OBS" moodCode="EVN">
                            <code code="DE04.30.009.00" codeSystem="2.16.156.10011.2.2.1" codeSystemName="卫生信息数据元目录" displayName="肺功能检查结果"/>
                            <value xsi:type="ST">未查</value>
                        </observation>
                    </entry>
                    <!-- 血常规检查结果 -->
                    <entry>
                        <observation classCode="OBS" moodCode="EVN">
                            <code code="DE04.50.128.00" codeSystem="2.16.156.10011.2.2.1" codeSystemName="卫生信息数据元目录" displayName="血常规检查结果"/>
                            <value xsi:type="ST">未查</value>
                        </observation>
                    </entry>
                    <!-- 尿常规检查结果 -->
                    <entry>
                        <observation classCode="OBS" moodCode="EVN">
                            <code code="DE04.50.048.00" codeSystem="2.16.156.10011.2.2.1" codeSystemName="卫生信息数据元目录" displayName="尿常规检查结果"/>
                            <value xsi:type="ST">未查</value>
                        </observation>
                    </entry>
                    <!-- 凝血功能检查结果 -->
                    <entry>
                        <observation classCode="OBS" moodCode="EVN">
                            <code code="DE04.50.142.00" codeSystem="2.16.156.10011.2.2.1" codeSystemName="卫生信息数据元目录" displayName="凝血功能检查结果"/>
                            <value xsi:type="ST">未查</value>
                        </observation>
                    </entry>
                    <!-- 肝功能检查结果 -->
                    <entry>
                        <observation classCode="OBS" moodCode="EVN">
                            <code code="DE04.50.026.00" codeSystem="2.16.156.10011.2.2.1" codeSystemName="卫生信息数据元目录" displayName="肝功能检查结果"/>
                            <value xsi:type="ST">未查</value>
                        </observation>
                    </entry>
                    <!-- 血气分析检查结果 -->
                    <entry>
                        <observation classCode="OBS" moodCode="EVN">
                            <code code="DE04.50.128.00" codeSystem="2.16.156.10011.2.2.1" codeSystemName="卫生信息数据元目录" displayName="血气分析检查结果"/>
                            <value xsi:type="ST">未查</value>
                        </observation>
                    </entry>
                </section>
            </component>
            <!--
********************************************************
治疗计划章节
********************************************************
-->
            <component>
                <section>
                    <code code="18776-5" codeSystem="2.16.840.1.113883.6.1" codeSystemName="LOINC" displayName="TREATMENT PLAN"/>
                    <text/>
                    <!-- 拟实施手术及操作编码 DE06.00.093.00 -->
                    <entry>
                        <procedure classCode="PROC" moodCode="EVN">
                            <code code="55.3401" codeSystem="2.16.156.10011.2.3.3.12" codeSystemName="手术(操作)代码表(ICD-9-CM)" displayName="腹腔镜下左肾病损切除+肾周粘连松解术" xsi:type="CD"/>
                            <!--手术间编号-->
                            <entryRelationship typeCode="COMP">
                                <observation classCode="OBS" moodCode="EVN">
                                    <code code="DE06.00.256.00" codeSystem="2.16.156.10011.2.2.1" codeSystemName="卫生信息数据元目录" displayName="患者实施手术所在的手术室编号"/>
                                    <value xsi:type="ST">22</value>
                                </observation>
                            </entryRelationship>
                        </procedure>
                    </entry>
                    <entry>
                        <!-- 拟实施麻醉方法代码 -->
                        <observation classCode="OBS" moodCode="INT">
                            <code code="DE06.00.073.00" codeSystem="2.16.156.10011.2.2.1" codeSystemName="卫生信息数据元目录" displayName="拟实施麻醉方法代码"/>
                            <value code="1" codeSystem="2.16.156.10011.2.3.1.159" codeSystemName="麻醉方法代码表" displayName="全身麻醉" xsi:type="CD"/>
                            <!-- 术前麻醉医嘱 -->
                            <entryRelationship typeCode="COMP">
                                <observation classCode="OBS" moodCode="INT">
                                    <code code="DE06.00.287.00" codeSystem="2.16.156.10011.2.2.1" codeSystemName="卫生信息数据元目录" displayName="术前麻醉医嘱"/>
                                    <value xsi:type="ST">术前禁饮食，完善各项检查。</value>
                                </observation>
                            </entryRelationship>
                            <!-- 麻醉适应证 -->
                            <entryRelationship typeCode="COMP">
                                <observation classCode="OBS" moodCode="EVN">
                                    <code code="DE06.00.227.00" codeSystem="2.16.156.10011.2.2.1" codeSystemName="卫生信息数据元目录" displayName="麻醉适应证"/>
                                    <value xsi:type="ST">正常</value>
                                </observation>
                            </entryRelationship>
                            <!-- 注意事项 -->
                            <entryRelationship typeCode="COMP">
                                <observation classCode="OBS" moodCode="EVN">
                                    <code code="DE09.00.119.00" codeSystem="2.16.156.10011.2.2.1" codeSystemName="卫生信息数据元目录" displayName="注意事项"/>
                                    <value xsi:type="ST">术中输液，吸氧，监测生命体征，及时对症处理。</value>
                                </observation>
                            </entryRelationship>
                        </observation>
                    </entry>
                </section>
            </component>
        </structuredBody>
    </component>
</ClinicalDocument>