<ClinicalDocument xmlns="urn:hl7-org:v3" xmlns:mif="urn:hl7-org:v3/mif" xmlns:xsi="http://www.w3.org/2001/XMLSchema-instance" xsi:schemaLocation="urn:hl7-org:v3 ..sdschemasSDA.xsd">
    <realmCode code="CN"/>
    <typeId extension="POCD_MT000040" root="2.16.840.1.113883.1.3"/>
    <templateId root="2.16.156.10011.2.1.1.52"/>
    <id extension="10026052_1C0032" root="2.16.156.10011.1.1"/>
    <code code="C0032" codeSystem="2.16.156.10011.2.4" codeSystemName="卫生信息共享文档规范编码体系"/>
    <title>住院病案首页</title>
    <effectiveTime value="20211130091135"/>
    <confidentialityCode code="N" codeSystem="2.16.840.1.113883.5.25" codeSystemName="Confidentiality" displayName="正常访问保密级别"/>
    <languageCode code="zh-CN"/>
    <setId/>
    <versionNumber/>
    <recordTarget contextControlCode="OP" typeCode="RCT">
        <patientRole classCode="PAT">
            <id extension="370304198904212228" root="2.16.156.10011.1.19"/>
            <id extension="10026052_1" root="2.16.156.10011.1.12"/>
            <id extension="10026052" root="2.16.156.10011.1.13"/>
            <addr use="H">
                <houseNumber>苗山镇常庄村</houseNumber>
                <streetName>苗山镇常庄村</streetName>
                <township>苗山镇常庄村</township>
                <county>莱芜区</county>
                <city>济南市</city>
                <state>山东省</state>
                <postalCode>255000</postalCode>
            </addr>
            <telecom value="18363457318"/>
            <patient classCode="PSN" determinerCode="INSTANCE">
                <id extension="370304198904212228" root="2.16.156.10011.1.3"/>
                <name>李珍</name>
                <administrativeGenderCode code="2" codeSystem="2.16.156.10011.2.3.3.4" codeSystemName="生理性别代码表(GB/T 2261.1)" displayName="女性"/>
                <birthTime value="19890421"/>
                <maritalStatusCode code="20" codeSystem="2.16.156.10011.2.3.3.5" codeSystemName="婚姻状况代码表(GB/T 2261.2)" displayName="已婚"/>
                <ethnicGroupCode code="01" codeSystem="2.16.156.10011.2.3.3.3" codeSystemName="民族类别代码表(GB 3304)" displayName="汉族"/>
                <birthplace>
                    <place classCode="PLC" determinerCode="INSTANCE">
                        <addr>
                            <county>博山区</county>
                            <city>淄博市</city>
                            <state>山东省</state>
                            <postalCode>255000</postalCode>
                        </addr>
                    </place>
                </birthplace>
                <nationality code="156" codeSystem="2.16.156.10011.2.3.3.1" codeSystemName="世界各国和地区名称代码(GB/T 2659)" displayName="中国"/>
                <age unit="岁" value="33"/>
                <employerOrganization>
                    <name>-</name>
                    <telecom value="-"/>
                    <addr use="WP">
                        <houseNumber>-</houseNumber>
                        <streetName>-</streetName>
                        <township>-</township>
                        <county>-</county>
                        <city>-</city>
                        <state>-</state>
                        <postalCode>370000</postalCode>
                    </addr>
                </employerOrganization>
                <household>
                    <place classCode="PLC" determinerCode="INSTANCE">
                        <addr>
                            <houseNumber>博山镇下瓦泉村</houseNumber>
                            <streetName>博山镇下瓦泉村</streetName>
                            <township>博山镇下瓦泉村</township>
                            <county>中国</county>
                            <city>370000</city>
                            <state>博山镇下瓦泉村</state>
                            <postalCode>255000</postalCode>
                        </addr>
                    </place>
                </household>
                <nativePlace>
                    <place classCode="PLC" determinerCode="INSTANCE">
                        <addr>
                            <city>淄博市</city>
                            <state>山东省</state>
                        </addr>
                    </place>
                </nativePlace>
                <occupation>
                    <occupationCode code="24" codeSystem="2.16.156.10011.2.3.3.13" codeSystemName="从业状况(个人身体)代码表(GB/T 2261.4)" displayName="工人"/>
                </occupation>
            </patient>
            <providerOrganization classCode="ORG" determinerCode="INSTANCE">
                <id extension="49438123-6" root="2.16.156.10011.1.5"/>
                <name>济南市人民医院</name>
            </providerOrganization>
        </patientRole>
    </recordTarget>
    <author contextControlCode="OP" typeCode="AUT">
        <time value="20211119101620"/>
        <assignedAuthor classCode="ASSIGNED">
            <id extension="Y16WMQ" root="2.16.156.10011.1.7"/>
            <assignedPerson>
                <name>吴茂勤</name>
            </assignedPerson>
        </assignedAuthor>
    </author>
    <custodian typeCode="CST">
        <assignedCustodian classCode="ASSIGNED">
            <representedCustodianOrganization classCode="ORG" determinerCode="INSTANCE">
                <id extension="49438123-6" root="2.16.156.10011.1.5"/>
                <name>济南市人民医院</name>
            </representedCustodianOrganization>
        </assignedCustodian>
    </custodian>
    <legalAuthenticator>
        <time value="20211119101620"/>
        <signatureCode/>
        <assignedEntity>
            <id extension="Y16WMQ" root="2.16.156.10011.1.4"/>
            <code displayName="科主任"/>
            <assignedPerson classCode="PSN" determinerCode="INSTANCE">
                <name>吴茂勤</name>
            </assignedPerson>
        </assignedEntity>
    </legalAuthenticator>
    <authenticator>
        <time value="20211119101620"/>
        <signatureCode/>
        <assignedEntity>
            <id extension="Y16WMQ" root="2.16.156.10011.1.4"/>
            <code displayName="主任(副主任)医师"/>
            <assignedPerson classCode="PSN" determinerCode="INSTANCE">
                <name>吴茂勤</name>
            </assignedPerson>
        </assignedEntity>
    </authenticator>
    <authenticator>
        <time value="20211119101620"/>
        <signatureCode/>
        <assignedEntity>
            <id extension="MNWCK" root="2.16.156.10011.1.4"/>
            <code displayName="主治医师"/>
            <assignedPerson classCode="PSN" determinerCode="INSTANCE">
                <name>陈凯</name>
            </assignedPerson>
        </assignedEntity>
    </authenticator>
    <authenticator>
        <time value="20211119101620"/>
        <signatureCode/>
        <assignedEntity>
            <id extension="01129" root="2.16.156.10011.1.4"/>
            <code displayName="住院医师"/>
            <assignedPerson classCode="PSN" determinerCode="INSTANCE">
                <name>王群</name>
            </assignedPerson>
        </assignedEntity>
    </authenticator>
    <authenticator>
        <time value="20211119101620"/>
        <signatureCode/>
        <assignedEntity>
            <id extension="CKCR" root="2.16.156.10011.1.4"/>
            <code displayName="责任护士"/>
            <assignedPerson classCode="PSN" determinerCode="INSTANCE">
                <name>常蕊</name>
            </assignedPerson>
        </assignedEntity>
    </authenticator>
    <authenticator>
        <time value="20211119101620"/>
        <signatureCode/>
        <assignedEntity>
            <id extension="jx001" root="2.16.156.10011.1.4"/>
            <code displayName="进修医师"/>
            <assignedPerson classCode="PSN" determinerCode="INSTANCE">
                <name>进修医师</name>
            </assignedPerson>
        </assignedEntity>
    </authenticator>
    <authenticator>
        <time value="20211116111208"/>
        <signatureCode/>
        <assignedEntity>
            <id extension="sx001" root="2.16.156.10011.1.4"/>
            <code displayName="实习医师"/>
            <assignedPerson classCode="PSN" determinerCode="INSTANCE">
                <name>实习医师</name>
            </assignedPerson>
        </assignedEntity>
    </authenticator>
    <authenticator>
        <time value="20211119101620"/>
        <signatureCode/>
        <assignedEntity>
            <id extension="NSKGW" root="2.16.156.10011.1.4"/>
            <code displayName="编码员"/>
            <assignedPerson classCode="PSN" determinerCode="INSTANCE">
                <name>郭伟</name>
            </assignedPerson>
        </assignedEntity>
    </authenticator>
    <participant typeCode="NOT">
        <associatedEntity classCode="ECON">
            <code code="8" codeSystem="2.16.156.10011.2.3.3.8" codeSystemName="家庭关系代码表(GB/T 4761)" displayName="其他"/>
            <addr use="H">
                <houseNumber>博山镇下瓦泉村</houseNumber>
                <streetName>博山镇下瓦泉村</streetName>
                <township>博山镇下瓦泉村</township>
                <county>莱芜区</county>
                <city>济南市</city>
                <state>山东省</state>
                <postalCode>博山镇下瓦泉村</postalCode>
            </addr>
            <telecom use="H" value="博山镇下瓦泉村"/>
            <associatedPerson classCode="PSN" determinerCode="INSTANCE">
                <name>徐先美</name>
            </associatedPerson>
        </associatedEntity>
    </participant>
    <relatedDocument typeCode="RPLC">
        <parentDocument>
            <id/>
            <setId/>
            <versionNumber/>
        </parentDocument>
    </relatedDocument>
    <componentOf typeCode="COMP">
        <encompassingEncounter classCode="ENC" moodCode="EVN">
            <code code="1" codeSystem="2.16.156.10011.2.3.1.270" codeSystemName="入院途径代码表" displayName="门诊"/>
            <effectiveTime>
                <low value="20211116100130"/>
                <high value="20211116111208"/>
            </effectiveTime>
            <location typeCode="LOC">
                <healthCareFacility classCode="SDLOC">
                    <serviceProviderOrganization classCode="ORG" determinerCode="INSTANCE">
                        <asOrganizationPartOf classCode="PART">
                            <wholeOrganization classCode="ORG" determinerCode="INSTANCE">
                                <id extension="6" root="2.16.156.10011.1.21"/>
                                <name>6</name>
                                <asOrganizationPartOf classCode="PART">
                                    <wholeOrganization classCode="ORG" determinerCode="INSTANCE">
                                        <id extension="3302" root="2.16.156.10011.1.26"/>
                                        <name>产二科病区</name>
                                    </wholeOrganization>
                                </asOrganizationPartOf>
                            </wholeOrganization>
                        </asOrganizationPartOf>
                    </serviceProviderOrganization>
                </healthCareFacility>
            </location>
        </encompassingEncounter>
    </componentOf>
    <component>
        <structuredBody>
            <component>
                <section>
                    <code code="8716-3" codeSystem="2.16.840.1.113883.6.1" codeSystemName="LOINC" displayName="VITAL SIGNS"/>
                    <text/>
                    <entry>
                        <observation classCode="OBS" moodCode="EVN">
                            <code code="DE04.10.019.00" codeSystem="2.16.156.10011.2.2.1" codeSystemName="卫生信息数据元目录" displayName="入院体重">
                                <qualifier>
                                    <name displayName="新生儿入院体重"/>
                                </qualifier>
                            </code>
                            <value unit="g" xsi:type="PQ"/>
                        </observation>
                    </entry>
                    <entry>
                        <observation classCode="OBS" moodCode="EVN">
                            <code code="DE04.10.019.00" codeSystem="2.16.156.10011.2.2.1" codeSystemName="卫生信息数据元目录" displayName="出生体重">
                                <qualifier>
                                    <name displayName="新生儿出生体重"/>
                                </qualifier>
                            </code>
                            <value unit="g" value="4200" xsi:type="PQ"/>
                        </observation>
                    </entry>
                </section>
            </component>
            <component>
                <section>
                    <code code="29548-5" codeSystem="2.16.840.1.113883.6.1" codeSystemName="LOINC" displayName="Diagnosis"/>
                    <text/>
                    <entry>
                        <organizer classCode="CLUSTER" moodCode="EVN">
                            <statusCode/>
                            <component>
                                <observation classCode="OBS" moodCode="EVN">
                                    <code code="DE05.01.025.00" codeSystem="2.16.156.10011.2.2.1" codeSystemName="卫生信息数据元目录" displayName="门（急）诊诊断名称">
                                        <qualifier>
                                            <name displayName="门（急）诊诊断"/>
                                        </qualifier>
                                    </code>
                                    <value xsi:type="ST">妊娠合并巨大儿</value>
                                </observation>
                            </component>
                            <component>
                                <observation classCode="OBS" moodCode="EVN">
                                    <code code="DE05.01.024.00" codeSystem="2.16.156.10011.2.2.1" codeSystemName="卫生信息数据元目录" displayName="门（急）诊诊断疾病编码">
                                        <qualifier>
                                            <name displayName="门（急）诊诊断"/>
                                        </qualifier>
                                    </code>
                                    <value code="O36.601" codeSystem="2.16.156.10011.2.3.3.11" codeSystemName="ICD-10" displayName="妊娠合并巨大儿" xsi:type="CD"/>
                                </observation>
                            </component>
                        </organizer>
                    </entry>
                    <entry>
                        <organizer classCode="CLUSTER" moodCode="EVN">
                            <statusCode/>
                            <component>
                                <observation classCode="OBS" moodCode="EVN">
                                    <id root="2.16.156.10011.1.8"/>
                                    <code code="DE05.01.025.00" codeSystem="2.16.156.10011.2.2.1" codeSystemName="卫生信息数据元目录" displayName="病理诊断-疾病名称">
                                        <qualifier>
                                            <name displayName="病理诊断"/>
                                        </qualifier>
                                    </code>
                                    <value xsi:type="ST">妊娠合并巨大儿</value>
                                </observation>
                            </component>
                            <component>
                                <observation classCode="OBS" moodCode="EVN">
                                    <code code="DE05.01.024.00" codeSystem="2.16.156.10011.2.2.1" codeSystemName="卫生信息数据元目录" displayName="病理诊断-疾病编码">
                                        <qualifier>
                                            <name displayName="病理诊断"/>
                                        </qualifier>
                                    </code>
                                    <value code="O36.601" codeSystem="2.16.156.10011.2.3.3.11" codeSystemName="ICD-10" displayName="妊娠合并巨大儿" xsi:type="CD"/>
                                </observation>
                            </component>
                        </organizer>
                    </entry>
                </section>
            </component>
            <component>
                <section>
                    <code code="11450-4" codeSystem="2.16.840.1.113883.6.1" codeSystemName="LOINC" displayName="PROBLEM LIST"/>
                    <text/>
                    <entry typeCode="COMP">
                        <observation classCode="OBS" moodCode="EVN">
                            <code code="DE05.10.119.00" codeSystem="2.16.156.10011.2.2.1" codeSystemName="卫生信息数据元目录" displayName="住院者疾病状态代码"/>
                            <value code="1" codeSystem="2.16.156.10011.2.3.1.100" codeSystemName="住院者疾病状态代码表" xsi:type="CD"/>
                        </observation>
                    </entry>
                    <entry typeCode="COMP">
                        <organizer classCode="CLUSTER" moodCode="EVN">
                            <code displayName="颅脑损伤患者入院前昏迷时间"/>
                            <statusCode/>
                            <component>
                                <observation classCode="OBS" moodCode="EVN">
                                    <code code="DE05.10.138.01" codeSystem="2.16.156.10011.2.2.1" codeSystemName="卫生信息数据元目录" displayName="颅脑损伤患者入院前昏迷时间-d"/>
                                    <value unit="d" value="0" xsi:type="PQ"/>
                                </observation>
                            </component>
                            <component>
                                <observation classCode="OBS" moodCode="EVN">
                                    <code code="DE05.10.138.02" codeSystem="2.16.156.10011.2.2.1" codeSystemName="卫生信息数据元目录" displayName="颅脑损伤患者入院前昏迷时间-h"/>
                                    <value unit="h" value="0" xsi:type="PQ"/>
                                </observation>
                            </component>
                            <component>
                                <observation classCode="OBS" moodCode="EVN">
                                    <code code="DE05.10.138.03" codeSystem="2.16.156.10011.2.2.1" codeSystemName="卫生信息数据元目录" displayName="颅脑损伤患者入院前昏迷时间-min"/>
                                    <value unit="min" value="0" xsi:type="PQ"/>
                                </observation>
                            </component>
                        </organizer>
                    </entry>
                    <entry typeCode="COMP">
                        <organizer classCode="CLUSTER" moodCode="EVN">
                            <code displayName="颅脑损伤患者入院后昏迷时间"/>
                            <statusCode/>
                            <component>
                                <observation classCode="OBS" moodCode="EVN">
                                    <code code="DE05.10.138.01" codeSystem="2.16.156.10011.2.2.1" codeSystemName="卫生信息数据元目录" displayName="颅脑损伤患者入院后昏迷时间-d"/>
                                    <value unit="d" value="0" xsi:type="PQ"/>
                                </observation>
                            </component>
                            <component>
                                <observation classCode="OBS" moodCode="EVN">
                                    <code code="DE05.10.138.02" codeSystem="2.16.156.10011.2.2.1" codeSystemName="卫生信息数据元目录" displayName="颅脑损伤患者入院后昏迷时间-h"/>
                                    <value unit="h" value="0" xsi:type="PQ"/>
                                </observation>
                            </component>
                            <component>
                                <observation classCode="OBS" moodCode="EVN">
                                    <code code="DE05.10.138.03" codeSystem="2.16.156.10011.2.2.1" codeSystemName="卫生信息数据元目录" displayName="颅脑损伤患者入院后昏迷时间-min"/>
                                    <value unit="min" value="0" xsi:type="PQ"/>
                                </observation>
                            </component>
                        </organizer>
                    </entry>
                </section>
            </component>
            <component>
                <section>
                    <code code="11535-2" codeSystem="2.16.840.1.113883.6.1" codeSystemName="LOINC" displayName="HOSPITAL DISCHARGE DX"/>
                    <text/>
                    <entry>
                        <organizer classCode="CLUSTER" moodCode="EVN">
                            <statusCode/>
                            <component>
                                <observation classCode="OBS" moodCode="EVN">
                                    <code code="DE05.01.025.00" codeSystem="2.16.156.10011.2.2.1" codeSystemName="卫生信息数据元目录" displayName="出院诊断-其他诊断名称">
                                        <qualifier>
                                            <name displayName="其他诊断名称"/>
                                        </qualifier>
                                    </code>
                                    <effectiveTime value="20211116"/>
                                    <value xsi:type="ST">妊娠合并巨大儿</value>
                                </observation>
                            </component>
                            <component>
                                <observation classCode="OBS" moodCode="EVN">
                                    <code code="DE05.01.024.00" codeSystem="2.16.156.10011.2.2.1" codeSystemName="卫生信息数据元目录" displayName="出院诊断-其他诊断疾病编码">
                                        <qualifier>
                                            <name displayName="其他诊断疾病编码"/>
                                        </qualifier>
                                    </code>
                                    <value code="O36.601" codeSystem="2.16.156.10011.2.3.3.11" codeSystemName="ICD-10" displayName="妊娠合并巨大儿" xsi:type="CD"/>
                                </observation>
                            </component>
                            <component>
                                <observation classCode="OBS" moodCode="EVN">
                                    <code code="DE09.00.104.00" codeSystem="2.16.156.10011.2.2.1" codeSystemName="卫生信息数据元目录" displayName="出院诊断-其他诊断入院病情代码">
                                        <qualifier>
                                            <name displayName="其他诊断入院病情代码"/>
                                        </qualifier>
                                    </code>
                                    <value code="O36.601" codeSystem="2.16.156.10011.2.3.1.253" codeSystemName="入院病情代码表" displayName="无" xsi:type="CD"/>
                                </observation>
                            </component>
                        </organizer>
                    </entry>
                    <entry>
                        <organizer classCode="CLUSTER" moodCode="EVN">
                            <statusCode/>
                            <component>
                                <observation classCode="OBS" moodCode="EVN">
                                    <code code="DE05.01.025.00" codeSystem="2.16.156.10011.2.2.1" codeSystemName="卫生信息数据元目录" displayName="出院诊断-主要诊断名称">
                                        <qualifier>
                                            <name displayName="主要诊断名称"/>
                                        </qualifier>
                                    </code>
                                    <effectiveTime value="20211116"/>
                                    <value xsi:type="ST">妊娠合并巨大儿</value>
                                </observation>
                            </component>
                            <component>
                                <observation classCode="OBS" moodCode="EVN">
                                    <code code="DE05.01.024.00" codeSystem="2.16.156.10011.2.2.1" codeSystemName="卫生信息数据元目录" displayName="出院诊断-主要诊断疾病编码">
                                        <qualifier>
                                            <name displayName="主要诊断疾病编码"/>
                                        </qualifier>
                                    </code>
                                    <value code="O36.601" codeSystem="2.16.156.10011.2.3.3.11" codeSystemName="ICD-10" displayName="妊娠合并巨大儿" xsi:type="CD"/>
                                </observation>
                            </component>
                            <component>
                                <observation classCode="OBS" moodCode="EVN">
                                    <code code="DE09.00.104.00" codeSystem="2.16.156.10011.2.2.1" codeSystemName="卫生信息数据元目录" displayName="出院诊断-主要诊断入院病情代码">
                                        <qualifier>
                                            <name displayName="主要诊断入院病情代码"/>
                                        </qualifier>
                                    </code>
                                    <value code="O36.601" codeSystem="2.16.156.10011.2.3.1.253" codeSystemName="入院病情代码表" displayName="无" xsi:type="CD"/>
                                </observation>
                            </component>
                        </organizer>
                    </entry>
                    <entry typeCode="COMP">
                        <observation classCode="OBS" moodCode="EVN">
                            <code code="DE06.00.223.00" codeSystem="2.16.156.10011.2.2.1" codeSystemName="卫生信息数据元目录" displayName="离院方式"/>
                            <value code="1" codeSystem="2.16.156.10011.2.3.1.265" codeSystemName="离院方式代码表" displayName="医嘱离院" xsi:type="CD"/>
                            <entryRelationship negationInd="false" typeCode="COMP">
                                <observation classCode="OBS" moodCode="EVN">
                                    <code code="DE08.10.013.00" codeSystem="2.16.156.10011.2.2.1" codeSystemName="卫生信息数据元目录" displayName="拟接受医疗机构名称"/>
                                    <value xsi:type="ST">济南市人民医院</value>
                                </observation>
                            </entryRelationship>
                        </observation>
                    </entry>
                </section>
            </component>
            <component>
                <section>
                    <code code="30954-2" codeSystem="2.16.840.1.113883.6.1" codeSystemName="LOINC" displayName="STUDIES SUMMARY"/>
                    <text/>
                    <entry typeCode="COMP">
                        <organizer classCode="BATTERY" moodCode="EVN">
                            <statusCode/>
                            <component typeCode="COMP">
                                <observation classCode="OBS" moodCode="EVN">
                                    <code code="DE04.50.010.00" codeSystem="2.16.156.10011.2.2.1" codeSystemName="卫生信息数据元目录"/>
                                    <value code="4" codeSystem="2.16.156.10011.2.3.1.250" codeSystemName="Rh(D)血型代码表" displayName="未查" xsi:type="CD"/>
                                </observation>
                            </component>
                            <component typeCode="COMP">
                                <observation classCode="OBS" moodCode="EVN">
                                    <code code="DE04.50.001.00" codeSystem="2.16.156.10011.2.2.1" codeSystemName="卫生信息数据元目录"/>
                                    <value code="5" codeSystem="2.16.156.10011.2.3.1.85" codeSystemName="ABO血型代码表" displayName="未查" xsi:type="CD"/>
                                </observation>
                            </component>
                        </organizer>
                    </entry>
                </section>
            </component>
            <component>
                <section>
                    <code code="47519-4" codeSystem="2.16.840.1.113883.6.1" codeSystemName="LOINC" displayName="HISTORY OF PROCEDURES"/>
                    <text/>
                </section>
            </component>
            <component>
                <section>
                    <code code="11336-5" codeSystem="2.16.840.1.113883.6.1" codeSystemName="LOINC" displayName="HISTORY OF HOSPITALIZATIONS"/>
                    <text/>
                    <entry typeCode="COMP">
                        <observation classCode="OBS" moodCode="EVN">
                            <code code="DE02.10.090.00" codeSystem="2.16.156.10011.2.2.1" codeSystemName="卫生信息数据元目录" displayName="住院次数"/>
                            <value value="1" xsi:type="INT"/>
                        </observation>
                    </entry>
                </section>
            </component>
            <component>
                <section>
                    <code code="8648-8" codeSystem="2.16.840.1.113883.6.1" codeSystemName="LOINC" displayName="Hospital Course"/>
                    <text/>
                    <entry typeCode="COMP">
                        <observation classCode="OBS" moodCode="EVN">
                            <code code="DE06.00.310.00" codeSystem="2.16.156.10011.2.2.1" codeSystemName="卫生信息数据元目录" displayName="实际住院天数"/>
                            <value unit="天" value="1" xsi:type="PQ"/>
                        </observation>
                    </entry>
                    <entry>
                        <act classCode="ACT" moodCode="EVN">
                            <code/>
                            <author>
                                <time/>
                                <assignedAuthor>
                                    <id/>
                                    <representedOrganization>
                                        <id extension="6" root="2.16.156.10011.1.21"/>
                                        <name>产二科病区</name>
                                        <asOrganizationPartOf classCode="PART">
                                            <wholeOrganization classCode="ORG" determinerCode="INSTANCE">
                                                <id extension="3302" root="2.16.156.10011.1.26"/>
                                                <name>产二科病区</name>
                                            </wholeOrganization>
                                        </asOrganizationPartOf>
                                    </representedOrganization>
                                </assignedAuthor>
                            </author>
                        </act>
                    </entry>
                </section>
            </component>
            <component>
                <section>
                    <code displayName="行政管理"/>
                    <text/>
                    <entry typeCode="COMP">
                        <observation classCode="OBS" moodCode="EVN">
                            <code code="DE09.00.108.00" codeSystem="2.16.156.10011.2.2.1" codeSystemName="卫生信息数据元目录" displayName="死亡患者尸检标志"/>
                            <value value="false" xsi:type="BL"/>
                        </observation>
                    </entry>
                    <entry>
                        <observation classCode="OBS" moodCode="EVN">
                            <code code="DE09.00.103.00" codeSystem="2.16.156.10011.2.2.1" codeSystemName="卫生信息数据元目录" displayName="病案质量"/>
                            <effectiveTime value="20211116111208"/>
                            <value code="1" codeSystem="2.16.156.10011.2.3.2.29" codeSystemName="病案质量等级表" displayName="甲" xsi:type="CD"/>
                        </observation>
                    </entry>
                </section>
            </component>
            <component>
                <section>
                    <code code="18776-5" codeSystem="2.16.840.1.113883.6.1" codeSystemName="LOINC" displayName="TREATMENT PLAN"/>
                    <text/>
                    <entry>
                        <observation classCode="OBS" moodCode="EVN">
                            <code code="DE06.00.194.00" codeSystem="2.16.156.10011.2.2.1" codeSystemName="卫生信息数据元目录" displayName="出院31天内再住院标志"/>
                            <value value="false" xsi:type="BL"/>
                        </observation>
                    </entry>
                </section>
            </component>
            <component>
                <section>
                    <code code="48768-6" codeSystem="2.16.840.1.113883.6.1" codeSystemName="LOINC" displayName="PAYMENT SOURCES"/>
                    <text/>
                    <entry>
                        <observation classCode="OBS" moodCode="EVN">
                            <code code="DE07.00.007.00" codeSystem="2.16.156.10011.2.2.1" codeSystemName="卫生信息数据元目录" displayName="医疗付费方式代码"/>
                            <value code="99" codeSystem="2.16.156.10011.2.3.1.269" codeSystemName="医疗付费方式代码表" displayName="其他" xsi:type="CD"/>
                        </observation>
                    </entry>
                    <entry>
                        <observation classCode="OBS" moodCode="EVN">
                            <code code="HDSD00.11.142" codeSystem="2.16.156.10011.2.2.4" codeSystemName="住院病案首页基本数据集" displayName="住院总费用"/>
                            <value currency="元" value="2493.47" xsi:type="MO"/>
                        </observation>
                    </entry>
                    <entry>
                        <organizer classCode="CLUSTER" moodCode="EVN">
                            <statusCode/>
                            <component>
                                <observation classCode="OBS" moodCode="EVN">
                                    <code code="HDSD00.11.147" codeSystem="2.16.156.10011.2.2.4" codeSystemName="住院病案首页基本数据集" displayName="综合医疗服务费-一般医疗服务费"/>
                                    <value currency="元" value="0.00" xsi:type="MO"/>
                                </observation>
                            </component>
                            <component>
                                <observation classCode="OBS" moodCode="EVN">
                                    <code code="HDSD00.11.148" codeSystem="2.16.156.10011.2.2.4" codeSystemName="住院病案首页基本数据集" displayName="综合医疗服务费-一般治疗操作费"/>
                                    <value currency="元" value="719.00" xsi:type="MO"/>
                                </observation>
                            </component>
                            <component>
                                <observation classCode="OBS" moodCode="EVN">
                                    <code code="HDSD00.11.145" codeSystem="2.16.156.10011.2.2.4" codeSystemName="住院病案首页基本数据集" displayName="综合医疗服务费-护理费"/>
                                    <value currency="元" value="43.00" xsi:type="MO"/>
                                </observation>
                            </component>
                            <component>
                                <observation classCode="OBS" moodCode="EVN">
                                    <code code="HDSD00.11.146" codeSystem="2.16.156.10011.2.2.4" codeSystemName="住院病案首页基本数据集" displayName="综合医疗服务费-其他费用"/>
                                    <value currency="元" value="0.00" xsi:type="MO"/>
                                </observation>
                            </component>
                        </organizer>
                    </entry>
                    <entry>
                        <organizer classCode="CLUSTER" moodCode="EVN">
                            <statusCode/>
                            <component>
                                <observation classCode="OBS" moodCode="EVN">
                                    <code code="HDSD00.11.121" codeSystem="2.16.156.10011.2.2.4" codeSystemName="住院病案首页基本数据集" displayName="诊断-病理诊断费"/>
                                    <value currency="元" value="0.00" xsi:type="MO"/>
                                </observation>
                            </component>
                            <component>
                                <observation classCode="OBS" moodCode="EVN">
                                    <code code="HDSD00.11.123" codeSystem="2.16.156.10011.2.2.4" codeSystemName="住院病案首页基本数据集" displayName="诊断-实验室诊断费"/>
                                    <value currency="元" value="0.00" xsi:type="MO"/>
                                </observation>
                            </component>
                            <component>
                                <observation classCode="OBS" moodCode="EVN">
                                    <code code="HDSD00.11.124" codeSystem="2.16.156.10011.2.2.4" codeSystemName="住院病案首页基本数据集" displayName="诊断-影像学诊断费"/>
                                    <value currency="元" value="41.60" xsi:type="MO"/>
                                </observation>
                            </component>
                            <component>
                                <observation classCode="OBS" moodCode="EVN">
                                    <code code="HDSD00.11.122" codeSystem="2.16.156.10011.2.2.4" codeSystemName="住院病案首页基本数据集" displayName="诊断-临床诊断项目费"/>
                                    <value currency="元" value="0.00" xsi:type="MO"/>
                                </observation>
                            </component>
                        </organizer>
                    </entry>
                    <entry>
                        <organizer classCode="CLUSTER" moodCode="EVN">
                            <statusCode/>
                            <component>
                                <observation classCode="OBS" moodCode="EVN">
                                    <code code="HDSD00.11.129" codeSystem="2.16.156.10011.2.2.4" codeSystemName="住院病案首页基本数据集" displayName="治疗-非手术治疗项目费"/>
                                    <value currency="元" value="0.00" xsi:type="MO"/>
                                    <entryRelationship typeCode="COMP">
                                        <observation classCode="OBS" moodCode="EVN">
                                            <code code="HDSD00.11.130" codeSystem="2.16.156.10011.2.2.4" codeSystemName="住院病案首页基本数据集" displayName="治疗-非手术治疗项目费-临床物理治疗费"/>
                                            <value currency="元" value="0.00" xsi:type="MO"/>
                                        </observation>
                                    </entryRelationship>
                                </observation>
                            </component>
                            <component>
                                <observation classCode="OBS" moodCode="EVN">
                                    <code code="HDSD00.11.131" codeSystem="2.16.156.10011.2.2.4" codeSystemName="住院病案首页基本数据集" displayName="治疗-手术治疗费"/>
                                    <value currency="元" value="1219.00" xsi:type="MO"/>
                                    <entryRelationship typeCode="COMP">
                                        <observation classCode="OBS" moodCode="EVN">
                                            <code code="HDSD00.11.132" codeSystem="2.16.156.10011.2.2.4" codeSystemName="住院病案首页基本数据集" displayName="治疗-手术治疗费-麻醉费"/>
                                            <value currency="元" value="255.00" xsi:type="MO"/>
                                        </observation>
                                    </entryRelationship>
                                    <entryRelationship typeCode="COMP">
                                        <observation classCode="OBS" moodCode="EVN">
                                            <code code="HDSD00.11.133" codeSystem="2.16.156.10011.2.2.4" codeSystemName="住院病案首页基本数据集" displayName="治疗-手术治疗费-手术费"/>
                                            <value currency="元" value="964.00" xsi:type="MO"/>
                                        </observation>
                                    </entryRelationship>
                                </observation>
                            </component>
                        </organizer>
                    </entry>
                    <entry>
                        <observation classCode="OBS" moodCode="EVN">
                            <code code="HDSD00.11.055" codeSystem="2.16.156.10011.2.2.4" codeSystemName="住院病案首页基本数据集" displayName="康复费"/>
                            <value currency="元" value="0.00" xsi:type="MO"/>
                        </observation>
                    </entry>
                    <entry>
                        <observation classCode="OBS" moodCode="EVN">
                            <code code="HDSD00.11.136" codeSystem="2.16.156.10011.2.2.4" codeSystemName="住院病案首页基本数据集" displayName="中医治疗费"/>
                            <value currency="元" value="0.00" xsi:type="MO"/>
                        </observation>
                    </entry>
                    <entry>
                        <observation classCode="OBS" moodCode="EVN">
                            <code code="HDSD00.11.098" codeSystem="2.16.156.10011.2.2.4" codeSystemName="住院病案首页基本数据集" displayName="西药费"/>
                            <value currency="元" value="13.44" xsi:type="MO"/>
                            <entryRelationship typeCode="COMP">
                                <observation classCode="OBS" moodCode="EVN">
                                    <code code="HDSD00.11.099" codeSystem="2.16.156.10011.2.2.4" codeSystemName="住院病案首页基本数据集" displayName="西药费-抗菌药物费用"/>
                                    <value currency="元" value="0.00" xsi:type="MO"/>
                                </observation>
                            </entryRelationship>
                        </observation>
                    </entry>
                    <entry>
                        <organizer classCode="CLUSTER" moodCode="EVN">
                            <statusCode/>
                            <component>
                                <observation classCode="OBS" moodCode="EVN">
                                    <code code="HDSD00.11.135" codeSystem="2.16.156.10011.2.2.4" codeSystemName="住院病案首页基本数据集" displayName="中药费-中成药费"/>
                                    <value currency="元" value="0.00" xsi:type="MO"/>
                                </observation>
                            </component>
                        </organizer>
                    </entry>
                    <entry>
                        <organizer classCode="CLUSTER" moodCode="EVN">
                            <statusCode/>
                            <component>
                                <observation classCode="OBS" moodCode="EVN">
                                    <code code="HDSD00.11.115" codeSystem="2.16.156.10011.2.2.4" codeSystemName="住院病案首页基本数据集" displayName="血费"/>
                                    <value currency="元" value="0.00" xsi:type="MO"/>
                                </observation>
                            </component>
                            <component>
                                <observation classCode="OBS" moodCode="EVN">
                                    <code code="HDSD00.11.111" codeSystem="2.16.156.10011.2.2.4" codeSystemName="住院病案首页基本数据集" displayName="白蛋白类制品费"/>
                                    <value currency="元" value="0.00" xsi:type="MO"/>
                                </observation>
                            </component>
                            <component>
                                <observation classCode="OBS" moodCode="EVN">
                                    <code code="HDSD00.11.113" codeSystem="2.16.156.10011.2.2.4" codeSystemName="住院病案首页基本数据集" displayName="球蛋白类制品费"/>
                                    <value currency="元" value="0.00" xsi:type="MO"/>
                                </observation>
                            </component>
                            <component>
                                <observation classCode="OBS" moodCode="EVN">
                                    <code code="HDSD00.11.112" codeSystem="2.16.156.10011.2.2.4" codeSystemName="住院病案首页基本数据集" displayName="凝血因子类制品费"/>
                                    <value currency="元" value="0.00" xsi:type="MO"/>
                                </observation>
                            </component>
                            <component>
                                <observation classCode="OBS" moodCode="EVN">
                                    <code code="HDSD00.11.114" codeSystem="2.16.156.10011.2.2.4" codeSystemName="住院病案首页基本数据集" displayName="细胞因子类制品费"/>
                                    <value currency="元" value="0.00" xsi:type="MO"/>
                                </observation>
                            </component>
                        </organizer>
                    </entry>
                    <entry>
                        <organizer classCode="CLUSTER" moodCode="EVN">
                            <statusCode/>
                            <component>
                                <observation classCode="OBS" moodCode="EVN">
                                    <code code="HDSD00.11.038" codeSystem="2.16.156.10011.2.2.4" codeSystemName="住院病案首页基本数据集" displayName="一次性医用材料费-检查用"/>
                                    <value currency="元" value="0.00" xsi:type="MO"/>
                                </observation>
                            </component>
                            <component>
                                <observation classCode="OBS" moodCode="EVN">
                                    <code code="HDSD00.11.040" codeSystem="2.16.156.10011.2.2.4" codeSystemName="住院病案首页基本数据集" displayName="一次性医用材料费-治疗用"/>
                                    <value currency="元" value="294.73" xsi:type="MO"/>
                                </observation>
                            </component>
                            <component>
                                <observation classCode="OBS" moodCode="EVN">
                                    <code code="HDSD00.11.039" codeSystem="2.16.156.10011.2.2.4" codeSystemName="住院病案首页基本数据集" displayName="一次性医用材料费-手术用"/>
                                    <value currency="元" value="0.00" xsi:type="MO"/>
                                </observation>
                            </component>
                        </organizer>
                    </entry>
                </section>
            </component>
        </structuredBody>
    </component>
</ClinicalDocument>
